split_pdf_by_toc/__init__.py
split_pdf_by_toc/color_formatter.py
split_pdf_by_toc/main.py
split_pdf_by_toc/sanitize.py
split_pdf_by_toc-0.0.3.dist-info/licenses/LICENSE
split_pdf_by_toc-0.0.3.dist-info/METADATA
split_pdf_by_toc-0.0.3.dist-info/WHEEL
split_pdf_by_toc-0.0.3.dist-info/entry_points.txt
split_pdf_by_toc-0.0.3.dist-info/top_level.txt
split_pdf_by_toc-0.0.3.dist-info/RECORD
