Metadata-Version: 2.4
Name: split-pdf-by-toc
Version: 0.0.3
Summary: Splits a PDF by its TOC.
Requires-Python: >=3.12
License-File: LICENSE
Requires-Dist: pypdf>=6.6.0
Dynamic: license-file
